Weiser/__init__.py
Weiser/weiser.py
Weiser-0.1.dist-info/LICENSE
Weiser-0.1.dist-info/METADATA
Weiser-0.1.dist-info/WHEEL
Weiser-0.1.dist-info/top_level.txt
Weiser-0.1.dist-info/RECORD
