Metadata-Version: 2.1
Name: Weiser
Version: 0.1
Summary: Contains useful tools for data analysis @ C&Tech.
Home-page: https://github.com/weiserofficial/weiser
Author: sangyoon.lee
Author-email: sylee@cntech.pro
License: MIT
Keywords: cntech eda
Platform: UNKNOWN
Classifier: License :: OSI Approved :: MIT License
Classifier: Programming Language :: Python :: 3
Classifier: Programming Language :: Python :: 3.2
Classifier: Programming Language :: Python :: 3.3
Classifier: Programming Language :: Python :: 3.4
Classifier: Programming Language :: Python :: 3.5
Classifier: Programming Language :: Python :: 3.6
Classifier: Programming Language :: Python :: 3.7
Requires-Python: >=3
Requires-Dist: psycopg2
